ai_assistant_manager/__init__.py
ai_assistant_manager/encoding.py
ai_assistant_manager/env_variables.py
ai_assistant_manager/env_variables_test.py
ai_assistant_manager/named_bytes.py
ai_assistant_manager/assistants/__init__.py
ai_assistant_manager/assistants/assistant_service.py
ai_assistant_manager/assistants/assistant_service_test.py
ai_assistant_manager/chats/__init__.py
ai_assistant_manager/chats/chat.py
ai_assistant_manager/chats/chat_response.py
ai_assistant_manager/chats/chat_test.py
ai_assistant_manager/clients/__init__.py
ai_assistant_manager/clients/openai_api.py
ai_assistant_manager/clients/openai_api_test.py
ai_assistant_manager/exporters/__init__.py
ai_assistant_manager/exporters/content_data.py
ai_assistant_manager/exporters/exporter.py
ai_assistant_manager/exporters/exporter_test.py
ai_assistant_manager/exporters/directory/__init__.py
ai_assistant_manager/exporters/directory/directory_exporter.py
ai_assistant_manager/exporters/directory/directory_exporter_test.py
ai_assistant_manager/exporters/files/__init__.py
ai_assistant_manager/exporters/files/files_exporter.py
ai_assistant_manager/exporters/files/files_exporter_test.py
ai_assistant_manager/prompts/__init__.py
ai_assistant_manager/prompts/prompt.py
ai_assistant_manager/prompts/prompt_test.py
ai_assistant_manager/prompts/sample_prompt.md
ai_assistant_manager/prompts/sample_prompt_with_tool_call.md
ai_assistant_manager/timer/__init__.py
ai_assistant_manager/timer/timer.py
ai_assistant_manager/timer/timer_test.py
ai_assistant_manager/tools/__init__.py
ai_assistant_manager/tools/tools.json
ai_assistant_manager/tools/tools.py
ai_assistant_manager/tools/tools_test.py
ai_assistant_manager/tools/weather.py
ai_assistant_manager-2.13.0.dist-info/METADATA
ai_assistant_manager-2.13.0.dist-info/WHEEL
ai_assistant_manager-2.13.0.dist-info/licenses/LICENSE
ai_assistant_manager-2.13.0.dist-info/RECORD
