Metadata-Version: 2.3
Name: ai-assistant-manager
Version: 2.13.0
Summary: This repository provides tools and services to manage OpenAI Assistants, including creating, listing, and deleting assistants, as well as handling vector stores and retrieval files.
Project-URL: repository, https://github.com/DEV3L/open-ai-assistant
Author-email: Justin Beall <jus.beall@gmail.com>
License: /*
License-File: LICENSE
Keywords: AI,API,NLP,artificial intelligence,assistant,automation,chatbot,data science,deep learning,machine learning,management,natural language processing,openai,python,vector store
Classifier: Development Status :: 4 - Beta
Classifier: Intended Audience :: Developers
Classifier: License :: OSI Approved :: MIT License
Classifier: Programming Language :: Python :: 3
Classifier: Programming Language :: Python :: 3.11
Classifier: Topic :: Software Development :: Libraries :: Python Modules
Requires-Python: >=3.11
Requires-Dist: loguru
Requires-Dist: openai
Requires-Dist: python-dateutil
Requires-Dist: python-dotenv
Requires-Dist: twine
